Workbook

Sheet Wachstumsmotor
B2: AgenticIT · Proaktiver Wachstumsmotor
B3: Signal-getriggerte Automationen, die selbst Termine setzen, Leads generieren, verkaufen, verlängern und Empfehlungen holen
B5: So liest du diese Liste: Der Motor läuft in 7 Stufen – der Output jeder Stufe füttert die nächste (generierte Leads → Termine → Abschlüsse → Verlängerung & Expansion → Empfehlungen, die wieder neue Leads bringen). Der Unterschied zu normaler Automatisierung: Jede Zeile startet auf ein echtes KAUFSIGNAL, nicht nur auf einen Zeitplan. Der Prio-Score = Impact ÷ Aufwand zeigt die Quick Wins (höchster Score zuerst umsetzen).
B10: Die 7 Stufen des Motors
B11: Stufe | C11: Aufgabe im Motor | D11: Anzahl | E11: Ø Score
B12: 1 Lead-Gen | C12: Neue Leads aus Kaufsignalen finden | D12: =COUNTIF(Katalog!B:B,"1 Lead-Gen") -> 7 | E12: =ROUND(AVERAGEIF(Katalog!B:B,"1 Lead-Gen",Katalog!K:K),2) -> 1.88
B13: 2 Inbound | C13: Anfragen sofort packen (Speed-to-Lead) | D13: =COUNTIF(Katalog!B:B,"2 Inbound") -> 5 | E13: =ROUND(AVERAGEIF(Katalog!B:B,"2 Inbound",Katalog!K:K),2) -> 2.27
B14: 3 Termin-Setting | C14: Termine autonom vereinbaren | D14: =COUNTIF(Katalog!B:B,"3 Termin-Setting") -> 4 | E14: =ROUND(AVERAGEIF(Katalog!B:B,"3 Termin-Setting",Katalog!K:K),2) -> 2.92
B15: 4 Nurture | C15: Leads reifen & an Sales eskalieren | D15: =COUNTIF(Katalog!B:B,"4 Nurture") -> 5 | E15: =ROUND(AVERAGEIF(Katalog!B:B,"4 Nurture",Katalog!K:K),2) -> 2.4
B16: 5 Closing | C16: Deals proaktiv zum Abschluss treiben | D16: =COUNTIF(Katalog!B:B,"5 Closing") -> 6 | E16: =ROUND(AVERAGEIF(Katalog!B:B,"5 Closing",Katalog!K:K),2) -> 2.42
B17: 6 Renewal+Expansion | C17: Verlängern, Upsell & Churn retten | D17: =COUNTIF(Katalog!B:B,"6 Renewal+Expansion") -> 6 | E17: =ROUND(AVERAGEIF(Katalog!B:B,"6 Renewal+Expansion",Katalog!K:K),2) -> 2.83
B18: 7 Empfehlung | C18: Empfehlungen, Reviews & Advocacy ernten | D18: =COUNTIF(Katalog!B:B,"7 Empfehlung") -> 6 | E18: =ROUND(AVERAGEIF(Katalog!B:B,"7 Empfehlung",Katalog!K:K),2) -> 3.08
B19: Gesamt | D19: =SUM(D12:D18) -> 39
B21: Leitplanken (AgenticIT-Standard): Kundengerichtete KI klar kennzeichnen (AI-Disclosure). Outbound, Angebote, Verträge und Empfehlungs-Asks vor Versand menschlich freigeben (Human-in-the-loop). Nur öffentliche/eingewilligte Daten, DSGVO-konform. Autonomie-Level je Zeile zeigt, wie viel Mensch nötig ist.

Sheet Katalog
A1: Nr. | B1: Stufe | C1: Automatisierung / Use Case | D1: Proaktiver Auslöser (Signal) | E1: Ablauf (kurz) | F1: Tools (n8n) | G1: Wirkt auf (KPI) | H1: Erwarteter Uplift (indikativ) | I1: Impact (1-5) | J1: Aufwand (1-3) | K1: Prio-Score | L1: Autonomie-Level | M1: Branchen | N1: Compliance / Leitplanke
A2: 1 | B2: 1 Lead-Gen | C2: Intent-Signal-Prospecting | D2: Jobanzeige / Funding / Tech-Wechsel beim Zielkonto | E2: Kaufsignal erkennen → ICP-Match → angereicherte Liste + personalisierter Outreach-Entwurf. | F2: Apollo/Clay, OpenAI, CRM | G2: Pipeline-Volumen | H2: >+30% qualifizierte Leads | I2: 5 | J2: 3 | K2: =ROUND(I2/J2,2) -> 1.67 | L2: Assistiert | M2: B2B, SaaS, Agentur | N2: Nur öffentl. Daten; Human-Review vor Versand
A3: 2 | B3: 1 Lead-Gen | C3: Website-Visitor-Identifikation → Outbound | D3: Anonymer Firmen-Besucher auf High-Intent-Seite | E3: Besucher firmografisch identifizieren → SDR-Alert + passende Sequenz. | F3: Leadfeeder/RB2B, CRM, Slack | G3: Inbound→Outbound-Quote | H3: +20-40% genutzte Intent-Signale | I3: 5 | J3: 2 | K3: =ROUND(I3/J3,2) -> 2.5 | L3: Assistiert | M3: B2B, SaaS | N3: DSGVO: keine Personen-Identifikation ohne Basis
A4: 3 | B4: 1 Lead-Gen | C4: Social-Engagement-Mining | D4: Interaktion mit eigenem/Wettbewerber-Content | E4: Engager als Lead erfassen → Connect + kontextbezogene Nachricht. | F4: LinkedIn-API/PhantomBuster, CRM | G4: Top-of-Funnel | H4: Wärmere Leads, höhere Antwortrate | I4: 4 | J4: 2 | K4: =ROUND(I4/J4,2) -> 2 | L4: Assistiert | M4: B2B, Coaching, Agentur | N4: Plattform-AGB; kein Spam
A5: 4 | B5: 1 Lead-Gen | C5: Lookalike-Liste aus Best-Kunden | D5: Neuer Top-Kunde (Closed-Won) | E5: Merkmale extrahieren → ähnliche Firmen finden → Ziel-Liste bauen. | F5: Clay, Enrichment, CRM | G5: Listen-Qualität | H5: Treffsicherere Zielkonten | I5: 4 | J5: 2 | K5: =ROUND(I5/J5,2) -> 2 | L5: Halb-autonom | M5: B2B, Vertrieb | N5: DSGVO; Quellenprüfung
A6: 5 | B6: 1 Lead-Gen | C6: Trigger-Event-Monitoring (News/PR) | D6: Expansion, Leitungswechsel, Standorteröffnung | E6: Relevantes Event erkennen → Timing-perfekte, personalisierte Ansprache. | F6: News-API, OpenAI, CRM | G6: Antwortrate | H6: Höhere Relevanz & Reply-Rate | I6: 4 | J6: 2 | K6: =ROUND(I6/J6,2) -> 2 | L6: Assistiert | M6: B2B, Immobilien, Finanz | N6: Human-Review
A7: 6 | B7: 1 Lead-Gen | C7: Wettbewerber-Review-Mining | D7: Negative Bewertung beim Wettbewerber | E7: Unzufriedene Kunden erkennen → wertorientierter, taktvoller Outreach. | F7: Scraping (legal), OpenAI, CRM | G7: Switch-Pipeline | H7: Günstige Abwerbe-Chancen | I7: 3 | J7: 2 | K7: =ROUND(I7/J7,2) -> 1.5 | L7: Assistiert | M7: Lokal, E-Commerce, SaaS | N7: Fair, kein Bad-Mouthing; DSGVO
A8: 7 | B8: 1 Lead-Gen | C8: Regionale Lead-Recherche (Maps/Verzeichnisse) | D8: Neues Unternehmen/Branche in Zielregion | E8: Öffentliche Quellen sammeln → qualifizierte, angereicherte Liste. | F8: Maps-API, Sheets, OpenAI | G8: Listen-Aufbau | H8: Skalierbarer Listenbau | I8: 3 | J8: 2 | K8: =ROUND(I8/J8,2) -> 1.5 | L8: Halb-autonom | M8: Lokal, B2B-Dienstleistung | N8: Nur öffentl. Daten; DSGVO
A9: 8 | B9: 2 Inbound | C9: Speed-to-Lead < 60 Sekunden | D9: Inbound-Formular/Anfrage eingegangen | E9: Sofort SMS + Anruf-Routing + Terminslot, bevor der Lead abkühlt. | F9: Webhook, Twilio, Calendar, CRM | G9: Kontaktquote | H9: Bis 9x höhere Kontaktrate | I9: 5 | J9: 2 | K9: =ROUND(I9/J9,2) -> 2.5 | L9: Halb-autonom | M9: Alle, Immobilien, Versicherung | N9: Opt-in; AI-Disclosure bei Auto-SMS
A10: 9 | B10: 2 Inbound | C10: Lead-Magnet-Auslieferung + Sequenz | D10: Download/Opt-in abgeschlossen | E10: Asset sofort liefern → passende Nurture-Sequenz automatisch starten. | F10: Forms, E-Mail-Tool, CRM | G10: Lead→MQL | H10: Mehr aktivierte Leads | I10: 4 | J10: 1 | K10: =ROUND(I10/J10,2) -> 4 | L10: Autonom | M10: Alle, Coaching, B2B | N10: Werbe-Einwilligung
A11: 10 | B11: 2 Inbound | C11: KI-Chat-zu-Termin | D11: Website-Chat mit Kaufabsicht | E11: KI qualifiziert im Dialog und bucht direkt einen Termin. | F11: Chat-Widget, OpenAI, Calendar | G11: Demo-Buchungen | H11: +Conversion aus Web-Traffic | I11: 4 | J11: 2 | K11: =ROUND(I11/J11,2) -> 2 | L11: Halb-autonom | M11: SaaS, Dienstleistung | N11: AI-Disclosure Pflicht
A12: 11 | B12: 2 Inbound | C12: Inbound-Call-Qualifizierung (Voice-AI) | D12: Eingehender Anruf | E12: KI nimmt an, qualifiziert und bucht oder routet an Mensch. | F12: Voice-AI, Calendar, CRM | G12: Erreichbarkeit | H12: Keine verpassten Anfragen | I12: 4 | J12: 3 | K12: =ROUND(I12/J12,2) -> 1.33 | L12: Halb-autonom | M12: Praxis, Handwerk, Service | N12: AI-Disclosure; Aufzeichnungs-Einwilligung
A13: 12 | B13: 2 Inbound | C13: Recovery abgebrochener Formulare | D13: Formular begonnen, nicht abgeschickt | E13: Erfasste Daten nutzen → freundlicher Anstoß zur Fertigstellung. | F13: Form-Tracking, SMTP, CRM | G13: Formular-Conversion | H13: Zurückgewonnene Anfragen | I13: 3 | J13: 2 | K13: =ROUND(I13/J13,2) -> 1.5 | L13: Halb-autonom | M13: E-Commerce, SaaS, Versicherung | N13: DSGVO: nur mit Einwilligung
... A40: 39 | B40: 7 Empfehlung | C40: Partner-/Affiliate-Reaktivierung | D40: Partner X Tage inaktiv | E40: Reaktivierungs-Nudge + neue Anreize automatisch. | F40: CRM/PRM, SMTP | G40: Partner-Pipeline | H40: Mehr Umsatz über Partner | I40: 3 | J40: 2 | K40: =ROUND(I40/J40,2) -> 1.5 | L40: Halb-autonom | M40: SaaS, B2B, Handel | N40: —

Sheet Prio-Matrix
L1: Aufwand | M1: Impact | N1: Nr
B2: Priorisierungs-Matrix · Impact × Aufwand | L2: =Katalog!J2 -> 3 | M2: =Katalog!I2 -> 5 | N2: =Katalog!A2 -> 1
B3: Oben-links = Quick Wins (hoher Impact, niedriger Aufwand) zuerst umsetzen. Punkte = Nr. aus dem Katalog. | L3: =Katalog!J3 -> 2 | M3: =Katalog!I3 -> 5 | N3: =Katalog!A3 -> 2
L4: =Katalog!J4 -> 2 | M4: =Katalog!I4 -> 4 | N4: =Katalog!A4 -> 3
L5: =Katalog!J5 -> 2 | M5: =Katalog!I5 -> 4 | N5: =Katalog!A5 -> 4
L6: =Katalog!J6 -> 2 | M6: =Katalog!I6 -> 4 | N6: =Katalog!A6 -> 5
L7: =Katalog!J7 -> 2 | M7: =Katalog!I7 -> 3 | N7: =Katalog!A7 -> 6
L8: =Katalog!J8 -> 2 | M8: =Katalog!I8 -> 3 | N8: =Katalog!A8 -> 7
L9: =Katalog!J9 -> 2 | M9: =Katalog!I9 -> 5 | N9: =Katalog!A9 -> 8
L10: =Katalog!J10 -> 1 | M10: =Katalog!I10 -> 4 | N10: =Katalog!A10 -> 9
L11: =Katalog!J11 -> 2 | M11: =Katalog!I11 -> 4 | N11: =Katalog!A11 -> 10
L12: =Katalog!J12 -> 3 | M12: =Katalog!I12 -> 4 | N12: =Katalog!A12 -> 11
L13: =Katalog!J13 -> 2 | M13: =Katalog!I13 -> 3 | N13: =Katalog!A13 -> 12
L14: =Katalog!J14 -> 3 | M14: =Katalog!I14 -> 5 | N14: =Katalog!A14 -> 13
L15: =Katalog!J15 -> 1 | M15: =Katalog!I15 -> 4 | N15: =Katalog!A15 -> 14
... L40: =Katalog!J40 -> 2 | M40: =Katalog!I40 -> 3 | N40: =Katalog!A40 -> 39
